{"nodes": [{"id": "c_users_unicentrale_downloads_antigravity_services_gravity_api_app_ingestion_pipeline_py", "label": "pipeline.py", "file_type": "code", "source_file": "ingestion/pipeline.py", "source_location": "L1"}, {"id": "ingestion_pipeline_ingestionpipeline", "label": "IngestionPipeline", "file_type": "code", "source_file": "ingestion/pipeline.py", "source_location": "L34"}, {"id": "ingestion_pipeline_ingestionpipeline_init", "label": ".__init__()", "file_type": "code", "source_file": "ingestion/pipeline.py", "source_location": "L44"}, {"id": "ingestion_pipeline_ingestionpipeline_create", "label": ".create()", "file_type": "code", "source_file": "ingestion/pipeline.py", "source_location": "L73"}, {"id": "ingestion_pipeline_ingestionpipeline_ingest_from_url", "label": ".ingest_from_url()", "file_type": "code", "source_file": "ingestion/pipeline.py", "source_location": "L216"}, {"id": "ingestion_pipeline_ingestionpipeline_ingest_bytes", "label": ".ingest_bytes()", "file_type": "code", "source_file": "ingestion/pipeline.py", "source_location": "L267"}, {"id": "ingestion_pipeline_ingestionpipeline_parallel_index", "label": "._parallel_index()", "file_type": "code", "source_file": "ingestion/pipeline.py", "source_location": "L448"}, {"id": "documentmetadata", "label": "DocumentMetadata", "file_type": "code", "source_file": "ingestion/pipeline.py", "source_location": "L448"}, {"id": "ingestion_pipeline_ingestionpipeline_save_document_record", "label": "._save_document_record()", "file_type": "code", "source_file": "ingestion/pipeline.py", "source_location": "L628"}, {"id": "ingestion_pipeline_rationale_1", "label": "Gravity Search \u2014 Main Ingestion Pipeline Wires all processing, indexing, and kn", "file_type": "rationale", "source_file": "ingestion/pipeline.py", "source_location": "L1"}, {"id": "ingestion_pipeline_rationale_35", "label": "Main ingestion pipeline wiring all processing and indexing components.      Us", "file_type": "rationale", "source_file": "ingestion/pipeline.py", "source_location": "L35"}, {"id": "ingestion_pipeline_rationale_74", "label": "Factory: build a fully wired IngestionPipeline from app settings.         Grace", "file_type": "rationale", "source_file": "ingestion/pipeline.py", "source_location": "L74"}, {"id": "ingestion_pipeline_rationale_224", "label": "Download content from URL and ingest it.          Args:             url: HTTP", "file_type": "rationale", "source_file": "ingestion/pipeline.py", "source_location": "L224"}, {"id": "ingestion_pipeline_rationale_279", "label": "Full 7-step ingestion of raw bytes content.          Returns:             {", "file_type": "rationale", "source_file": "ingestion/pipeline.py", "source_location": "L279"}, {"id": "ingestion_pipeline_rationale_459", "label": "Run all indexers concurrently.", "file_type": "rationale", "source_file": "ingestion/pipeline.py", "source_location": "L459"}, {"id": "ingestion_pipeline_rationale_636", "label": "Persist the document, its normalized text (raw_text), and its chunks to", "file_type": "rationale", "source_file": "ingestion/pipeline.py", "source_location": "L636"}], "edges": [{"source": "c_users_unicentrale_downloads_antigravity_services_gravity_api_app_ingestion_pipeline_py", "target": "asyncio", "relation": "imports", "context": "import", "confidence": "EXTRACTED", "source_file": "ingestion/pipeline.py", "source_location": "L20", "weight": 1.0}, {"source": "c_users_unicentrale_downloads_antigravity_services_gravity_api_app_ingestion_pipeline_py", "target": "uuid", "relation": "imports", "context": "import", "confidence": "EXTRACTED", "source_file": "ingestion/pipeline.py", "source_location": "L21", "weight": 1.0}, {"source": "c_users_unicentrale_downloads_antigravity_services_gravity_api_app_ingestion_pipeline_py", "target": "structlog", "relation": "imports", "context": "import", "confidence": "EXTRACTED", "source_file": "ingestion/pipeline.py", "source_location": "L22", "weight": 1.0}, {"source": "c_users_unicentrale_downloads_antigravity_services_gravity_api_app_ingestion_pipeline_py", "target": "datetime", "relation": "imports_from", "context": "import", "confidence": "EXTRACTED", "source_file": "ingestion/pipeline.py", "source_location": "L23", "weight": 1.0}, {"source": "c_users_unicentrale_downloads_antigravity_services_gravity_api_app_ingestion_pipeline_py", "target": "app_ingestion_processing_document_processor", "relation": "imports_from", "context": "import", "confidence": "EXTRACTED", "source_file": "ingestion/pipeline.py", "source_location": "L25", "weight": 1.0}, {"source": "c_users_unicentrale_downloads_antigravity_services_gravity_api_app_ingestion_pipeline_py", "target": "app_ingestion_processing_metadata_extractor", "relation": "imports_from", "context": "import", "confidence": "EXTRACTED", "source_file": "ingestion/pipeline.py", "source_location": "L26", "weight": 1.0}, {"source": "c_users_unicentrale_downloads_antigravity_services_gravity_api_app_ingestion_pipeline_py", "target": "app_ingestion_processing_section_detector", "relation": "imports_from", "context": "import", "confidence": "EXTRACTED", "source_file": "ingestion/pipeline.py", "source_location": "L27", "weight": 1.0}, {"source": "c_users_unicentrale_downloads_antigravity_services_gravity_api_app_ingestion_pipeline_py", "target": "app_ingestion_processing_entity_extractor", "relation": "imports_from", "context": "import", "confidence": "EXTRACTED", "source_file": "ingestion/pipeline.py", "source_location": "L28", "weight": 1.0}, {"source": "c_users_unicentrale_downloads_antigravity_services_gravity_api_app_ingestion_pipeline_py", "target": "app_ingestion_processing_chunker", "relation": "imports_from", "context": "import", "confidence": "EXTRACTED", "source_file": "ingestion/pipeline.py", "source_location": "L29", "weight": 1.0}, {"source": "c_users_unicentrale_downloads_antigravity_services_gravity_api_app_ingestion_pipeline_py", "target": "ingestion_pipeline_ingestionpipeline", "relation": "contains", "confidence": "EXTRACTED", "source_file": "ingestion/pipeline.py", "source_location": "L34", "weight": 1.0}, {"source": "ingestion_pipeline_ingestionpipeline", "target": "ingestion_pipeline_ingestionpipeline_init", "relation": "method", "confidence": "EXTRACTED", "source_file": "ingestion/pipeline.py", "source_location": "L44", "weight": 1.0}, {"source": "ingestion_pipeline_ingestionpipeline", "target": "ingestion_pipeline_ingestionpipeline_create", "relation": "method", "confidence": "EXTRACTED", "source_file": "ingestion/pipeline.py", "source_location": "L73", "weight": 1.0}, {"source": "ingestion_pipeline_ingestionpipeline", "target": "ingestion_pipeline_ingestionpipeline_ingest_from_url", "relation": "method", "confidence": "EXTRACTED", "source_file": "ingestion/pipeline.py", "source_location": "L216", "weight": 1.0}, {"source": "ingestion_pipeline_ingestionpipeline", "target": "ingestion_pipeline_ingestionpipeline_ingest_bytes", "relation": "method", "confidence": "EXTRACTED", "source_file": "ingestion/pipeline.py", "source_location": "L267", "weight": 1.0}, {"source": "ingestion_pipeline_ingestionpipeline", "target": "ingestion_pipeline_ingestionpipeline_parallel_index", "relation": "method", "confidence": "EXTRACTED", "source_file": "ingestion/pipeline.py", "source_location": "L448", "weight": 1.0}, {"source": "ingestion_pipeline_ingestionpipeline_parallel_index", "target": "documentmetadata", "relation": "references", "context": "parameter_type", "confidence": "EXTRACTED", "source_file": "ingestion/pipeline.py", "source_location": "L448", "weight": 1.0}, {"source": "ingestion_pipeline_ingestionpipeline", "target": "ingestion_pipeline_ingestionpipeline_save_document_record", "relation": "method", "confidence": "EXTRACTED", "source_file": "ingestion/pipeline.py", "source_location": "L628", "weight": 1.0}, {"source": "ingestion_pipeline_ingestionpipeline_save_document_record", "target": "documentmetadata", "relation": "references", "context": "parameter_type", "confidence": "EXTRACTED", "source_file": "ingestion/pipeline.py", "source_location": "L628", "weight": 1.0}, {"source": "ingestion_pipeline_ingestionpipeline_ingest_from_url", "target": "ingestion_pipeline_ingestionpipeline_ingest_bytes", "relation": "calls", "context": "call", "confidence": "EXTRACTED", "source_file": "ingestion/pipeline.py", "source_location": "L256", "weight": 1.0}, {"source": "ingestion_pipeline_ingestionpipeline_ingest_bytes", "target": "ingestion_pipeline_ingestionpipeline_parallel_index", "relation": "calls", "context": "call", "confidence": "EXTRACTED", "source_file": "ingestion/pipeline.py", "source_location": "L405", "weight": 1.0}, {"source": "ingestion_pipeline_ingestionpipeline_ingest_bytes", "target": "ingestion_pipeline_ingestionpipeline_save_document_record", "relation": "calls", "context": "call", "confidence": "EXTRACTED", "source_file": "ingestion/pipeline.py", "source_location": "L419", "weight": 1.0}, {"source": "ingestion_pipeline_rationale_1", "target": "c_users_unicentrale_downloads_antigravity_services_gravity_api_app_ingestion_pipeline_py", "relation": "rationale_for", "confidence": "EXTRACTED", "source_file": "ingestion/pipeline.py", "source_location": "L1", "weight": 1.0}, {"source": "ingestion_pipeline_rationale_35", "target": "ingestion_pipeline_ingestionpipeline", "relation": "rationale_for", "confidence": "EXTRACTED", "source_file": "ingestion/pipeline.py", "source_location": "L35", "weight": 1.0}, {"source": "ingestion_pipeline_rationale_74", "target": "ingestion_pipeline_ingestionpipeline_create", "relation": "rationale_for", "confidence": "EXTRACTED", "source_file": "ingestion/pipeline.py", "source_location": "L74", "weight": 1.0}, {"source": "ingestion_pipeline_rationale_224", "target": "ingestion_pipeline_ingestionpipeline_ingest_from_url", "relation": "rationale_for", "confidence": "EXTRACTED", "source_file": "ingestion/pipeline.py", "source_location": "L224", "weight": 1.0}, {"source": "ingestion_pipeline_rationale_279", "target": "ingestion_pipeline_ingestionpipeline_ingest_bytes", "relation": "rationale_for", "confidence": "EXTRACTED", "source_file": "ingestion/pipeline.py", "source_location": "L279", "weight": 1.0}, {"source": "ingestion_pipeline_rationale_459", "target": "ingestion_pipeline_ingestionpipeline_parallel_index", "relation": "rationale_for", "confidence": "EXTRACTED", "source_file": "ingestion/pipeline.py", "source_location": "L459", "weight": 1.0}, {"source": "ingestion_pipeline_rationale_636", "target": "ingestion_pipeline_ingestionpipeline_save_document_record", "relation": "rationale_for", "confidence": "EXTRACTED", "source_file": "ingestion/pipeline.py", "source_location": "L636", "weight": 1.0}], "raw_calls": [{"caller_nid": "ingestion_pipeline_ingestionpipeline_init", "callee": "DocumentProcessor", "is_member_call": false, "source_file": "C:\\Users\\unicentrale\\Downloads\\antigravity\\services\\gravity-api\\app\\ingestion\\pipeline.py", "source_location": "L56"}, {"caller_nid": "ingestion_pipeline_ingestionpipeline_init", "callee": "MetadataExtractor", "is_member_call": false, "source_file": "C:\\Users\\unicentrale\\Downloads\\antigravity\\services\\gravity-api\\app\\ingestion\\pipeline.py", "source_location": "L57"}, {"caller_nid": "ingestion_pipeline_ingestionpipeline_init", "callee": "SectionDetector", "is_member_call": false, "source_file": "C:\\Users\\unicentrale\\Downloads\\antigravity\\services\\gravity-api\\app\\ingestion\\pipeline.py", "source_location": "L58"}, {"caller_nid": "ingestion_pipeline_ingestionpipeline_init", "callee": "EntityExtractor", "is_member_call": false, "source_file": "C:\\Users\\unicentrale\\Downloads\\antigravity\\services\\gravity-api\\app\\ingestion\\pipeline.py", "source_location": "L59"}, {"caller_nid": "ingestion_pipeline_ingestionpipeline_init", "callee": "HierarchicalChunker", "is_member_call": false, "source_file": "C:\\Users\\unicentrale\\Downloads\\antigravity\\services\\gravity-api\\app\\ingestion\\pipeline.py", "source_location": "L60"}, {"caller_nid": "ingestion_pipeline_ingestionpipeline_create", "callee": "get_embedder", "is_member_call": false, "source_file": "C:\\Users\\unicentrale\\Downloads\\antigravity\\services\\gravity-api\\app\\ingestion\\pipeline.py", "source_location": "L88"}, {"caller_nid": "ingestion_pipeline_ingestionpipeline_create", "callee": "get_splade_encoder", "is_member_call": false, "source_file": "C:\\Users\\unicentrale\\Downloads\\antigravity\\services\\gravity-api\\app\\ingestion\\pipeline.py", "source_location": "L94"}, {"caller_nid": "ingestion_pipeline_ingestionpipeline_create", "callee": "lower", "is_member_call": true, "source_file": "C:\\Users\\unicentrale\\Downloads\\antigravity\\services\\gravity-api\\app\\ingestion\\pipeline.py", "source_location": "L95"}, {"caller_nid": "ingestion_pipeline_ingestionpipeline_create", "callee": "getenv", "is_member_call": true, "source_file": "C:\\Users\\unicentrale\\Downloads\\antigravity\\services\\gravity-api\\app\\ingestion\\pipeline.py", "source_location": "L95"}, {"caller_nid": "ingestion_pipeline_ingestionpipeline_create", "callee": "VectorIndexer", "is_member_call": false, "source_file": "C:\\Users\\unicentrale\\Downloads\\antigravity\\services\\gravity-api\\app\\ingestion\\pipeline.py", "source_location": "L98"}, {"caller_nid": "ingestion_pipeline_ingestionpipeline_create", "callee": "warning", "is_member_call": true, "source_file": "C:\\Users\\unicentrale\\Downloads\\antigravity\\services\\gravity-api\\app\\ingestion\\pipeline.py", "source_location": "L100"}, {"caller_nid": "ingestion_pipeline_ingestionpipeline_create", "callee": "KeywordIndexer", "is_member_call": false, "source_file": "C:\\Users\\unicentrale\\Downloads\\antigravity\\services\\gravity-api\\app\\ingestion\\pipeline.py", "source_location": "L104"}, {"caller_nid": "ingestion_pipeline_ingestionpipeline_create", "callee": "warning", "is_member_call": true, "source_file": "C:\\Users\\unicentrale\\Downloads\\antigravity\\services\\gravity-api\\app\\ingestion\\pipeline.py", "source_location": "L106"}, {"caller_nid": "ingestion_pipeline_ingestionpipeline_create", "callee": "GraphIndexer", "is_member_call": false, "source_file": "C:\\Users\\unicentrale\\Downloads\\antigravity\\services\\gravity-api\\app\\ingestion\\pipeline.py", "source_location": "L111"}, {"caller_nid": "ingestion_pipeline_ingestionpipeline_create", "callee": "get_neo4j_driver", "is_member_call": false, "source_file": "C:\\Users\\unicentrale\\Downloads\\antigravity\\services\\gravity-api\\app\\ingestion\\pipeline.py", "source_location": "L111"}, {"caller_nid": "ingestion_pipeline_ingestionpipeline_create", "callee": "warning", "is_member_call": true, "source_file": "C:\\Users\\unicentrale\\Downloads\\antigravity\\services\\gravity-api\\app\\ingestion\\pipeline.py", "source_location": "L113"}, {"caller_nid": "ingestion_pipeline_ingestionpipeline_create", "callee": "lower", "is_member_call": true, "source_file": "C:\\Users\\unicentrale\\Downloads\\antigravity\\services\\gravity-api\\app\\ingestion\\pipeline.py", "source_location": "L117"}, {"caller_nid": "ingestion_pipeline_ingestionpipeline_create", "callee": "getenv", "is_member_call": true, "source_file": "C:\\Users\\unicentrale\\Downloads\\antigravity\\services\\gravity-api\\app\\ingestion\\pipeline.py", "source_location": "L117"}, {"caller_nid": "ingestion_pipeline_ingestionpipeline_create", "callee": "LLMRouter", "is_member_call": false, "source_file": "C:\\Users\\unicentrale\\Downloads\\antigravity\\services\\gravity-api\\app\\ingestion\\pipeline.py", "source_location": "L121"}, {"caller_nid": "ingestion_pipeline_ingestionpipeline_create", "callee": "get_fast_client", "is_member_call": true, "source_file": "C:\\Users\\unicentrale\\Downloads\\antigravity\\services\\gravity-api\\app\\ingestion\\pipeline.py", "source_location": "L122"}, {"caller_nid": "ingestion_pipeline_ingestionpipeline_create", "callee": "StructuredIndexer", "is_member_call": false, "source_file": "C:\\Users\\unicentrale\\Downloads\\antigravity\\services\\gravity-api\\app\\ingestion\\pipeline.py", "source_location": "L123"}, {"caller_nid": "ingestion_pipeline_ingestionpipeline_create", "callee": "warning", "is_member_call": true, "source_file": "C:\\Users\\unicentrale\\Downloads\\antigravity\\services\\gravity-api\\app\\ingestion\\pipeline.py", "source_location": "L125"}, {"caller_nid": "ingestion_pipeline_ingestionpipeline_create", "callee": "warning", "is_member_call": true, "source_file": "C:\\Users\\unicentrale\\Downloads\\antigravity\\services\\gravity-api\\app\\ingestion\\pipeline.py", "source_location": "L131"}, {"caller_nid": "ingestion_pipeline_ingestionpipeline_create", "callee": "PageIndexer", "is_member_call": false, "source_file": "C:\\Users\\unicentrale\\Downloads\\antigravity\\services\\gravity-api\\app\\ingestion\\pipeline.py", "source_location": "L138"}, {"caller_nid": "ingestion_pipeline_ingestionpipeline_create", "callee": "get_search_pipeline", "is_member_call": false, "source_file": "C:\\Users\\unicentrale\\Downloads\\antigravity\\services\\gravity-api\\app\\ingestion\\pipeline.py", "source_location": "L143"}, {"caller_nid": "ingestion_pipeline_ingestionpipeline_create", "callee": "get", "is_member_call": true, "source_file": "C:\\Users\\unicentrale\\Downloads\\antigravity\\services\\gravity-api\\app\\ingestion\\pipeline.py", "source_location": "L144"}, {"caller_nid": "ingestion_pipeline_ingestionpipeline_create", "callee": "set_search_channel", "is_member_call": true, "source_file": "C:\\Users\\unicentrale\\Downloads\\antigravity\\services\\gravity-api\\app\\ingestion\\pipeline.py", "source_location": "L146"}, {"caller_nid": "ingestion_pipeline_ingestionpipeline_create", "callee": "warning", "is_member_call": true, "source_file": "C:\\Users\\unicentrale\\Downloads\\antigravity\\services\\gravity-api\\app\\ingestion\\pipeline.py", "source_location": "L150"}, {"caller_nid": "ingestion_pipeline_ingestionpipeline_create", "callee": "TableIndexer", "is_member_call": false, "source_file": "C:\\Users\\unicentrale\\Downloads\\antigravity\\services\\gravity-api\\app\\ingestion\\pipeline.py", "source_location": "L157"}, {"caller_nid": "ingestion_pipeline_ingestionpipeline_create", "callee": "get_es_client", "is_member_call": false, "source_file": "C:\\Users\\unicentrale\\Downloads\\antigravity\\services\\gravity-api\\app\\ingestion\\pipeline.py", "source_location": "L160"}, {"caller_nid": "ingestion_pipeline_ingestionpipeline_create", "callee": "warning", "is_member_call": true, "source_file": "C:\\Users\\unicentrale\\Downloads\\antigravity\\services\\gravity-api\\app\\ingestion\\pipeline.py", "source_location": "L163"}, {"caller_nid": "ingestion_pipeline_ingestionpipeline_create", "callee": "lower", "is_member_call": true, "source_file": "C:\\Users\\unicentrale\\Downloads\\antigravity\\services\\gravity-api\\app\\ingestion\\pipeline.py", "source_location": "L171"}, {"caller_nid": "ingestion_pipeline_ingestionpipeline_create", "callee": "getenv", "is_member_call": true, "source_file": "C:\\Users\\unicentrale\\Downloads\\antigravity\\services\\gravity-api\\app\\ingestion\\pipeline.py", "source_location": "L171"}, {"caller_nid": "ingestion_pipeline_ingestionpipeline_create", "callee": "LLMRouter", "is_member_call": false, "source_file": "C:\\Users\\unicentrale\\Downloads\\antigravity\\services\\gravity-api\\app\\ingestion\\pipeline.py", "source_location": "L179"}, {"caller_nid": "ingestion_pipeline_ingestionpipeline_create", "callee": "RaptorIndexer", "is_member_call": false, "source_file": "C:\\Users\\unicentrale\\Downloads\\antigravity\\services\\gravity-api\\app\\ingestion\\pipeline.py", "source_location": "L180"}, {"caller_nid": "ingestion_pipeline_ingestionpipeline_create", "callee": "get_fast_client", "is_member_call": true, "source_file": "C:\\Users\\unicentrale\\Downloads\\antigravity\\services\\gravity-api\\app\\ingestion\\pipeline.py", "source_location": "L181"}, {"caller_nid": "ingestion_pipeline_ingestionpipeline_create", "callee": "get_embedder", "is_member_call": false, "source_file": "C:\\Users\\unicentrale\\Downloads\\antigravity\\services\\gravity-api\\app\\ingestion\\pipeline.py", "source_location": "L182"}, {"caller_nid": "ingestion_pipeline_ingestionpipeline_create", "callee": "warning", "is_member_call": true, "source_file": "C:\\Users\\unicentrale\\Downloads\\antigravity\\services\\gravity-api\\app\\ingestion\\pipeline.py", "source_location": "L185"}, {"caller_nid": "ingestion_pipeline_ingestionpipeline_create", "callee": "_CR_Router", "is_member_call": false, "source_file": "C:\\Users\\unicentrale\\Downloads\\antigravity\\services\\gravity-api\\app\\ingestion\\pipeline.py", "source_location": "L194"}, {"caller_nid": "ingestion_pipeline_ingestionpipeline_create", "callee": "ContextualRetrieval", "is_member_call": false, "source_file": "C:\\Users\\unicentrale\\Downloads\\antigravity\\services\\gravity-api\\app\\ingestion\\pipeline.py", "source_location": "L195"}, {"caller_nid": "ingestion_pipeline_ingestionpipeline_create", "callee": "get_fast_client", "is_member_call": true, "source_file": "C:\\Users\\unicentrale\\Downloads\\antigravity\\services\\gravity-api\\app\\ingestion\\pipeline.py", "source_location": "L196"}, {"caller_nid": "ingestion_pipeline_ingestionpipeline_create", "callee": "warning", "is_member_call": true, "source_file": "C:\\Users\\unicentrale\\Downloads\\antigravity\\services\\gravity-api\\app\\ingestion\\pipeline.py", "source_location": "L199"}, {"caller_nid": "ingestion_pipeline_ingestionpipeline_create", "callee": "info", "is_member_call": true, "source_file": "C:\\Users\\unicentrale\\Downloads\\antigravity\\services\\gravity-api\\app\\ingestion\\pipeline.py", "source_location": "L202"}, {"caller_nid": "ingestion_pipeline_ingestionpipeline_create", "callee": "cls", "is_member_call": false, "source_file": "C:\\Users\\unicentrale\\Downloads\\antigravity\\services\\gravity-api\\app\\ingestion\\pipeline.py", "source_location": "L204"}, {"caller_nid": "ingestion_pipeline_ingestionpipeline_ingest_from_url", "callee": "info", "is_member_call": true, "source_file": "C:\\Users\\unicentrale\\Downloads\\antigravity\\services\\gravity-api\\app\\ingestion\\pipeline.py", "source_location": "L239"}, {"caller_nid": "ingestion_pipeline_ingestionpipeline_ingest_from_url", "callee": "AsyncClient", "is_member_call": true, "source_file": "C:\\Users\\unicentrale\\Downloads\\antigravity\\services\\gravity-api\\app\\ingestion\\pipeline.py", "source_location": "L242"}, {"caller_nid": "ingestion_pipeline_ingestionpipeline_ingest_from_url", "callee": "get", "is_member_call": true, "source_file": "C:\\Users\\unicentrale\\Downloads\\antigravity\\services\\gravity-api\\app\\ingestion\\pipeline.py", "source_location": "L243"}, {"caller_nid": "ingestion_pipeline_ingestionpipeline_ingest_from_url", "callee": "raise_for_status", "is_member_call": true, "source_file": "C:\\Users\\unicentrale\\Downloads\\antigravity\\services\\gravity-api\\app\\ingestion\\pipeline.py", "source_location": "L248"}, {"caller_nid": "ingestion_pipeline_ingestionpipeline_ingest_from_url", "callee": "split", "is_member_call": true, "source_file": "C:\\Users\\unicentrale\\Downloads\\antigravity\\services\\gravity-api\\app\\ingestion\\pipeline.py", "source_location": "L250"}, {"caller_nid": "ingestion_pipeline_ingestionpipeline_ingest_from_url", "callee": "get", "is_member_call": true, "source_file": "C:\\Users\\unicentrale\\Downloads\\antigravity\\services\\gravity-api\\app\\ingestion\\pipeline.py", "source_location": "L250"}, {"caller_nid": "ingestion_pipeline_ingestionpipeline_ingest_from_url", "callee": "error", "is_member_call": true, "source_file": "C:\\Users\\unicentrale\\Downloads\\antigravity\\services\\gravity-api\\app\\ingestion\\pipeline.py", "source_location": "L252"}, {"caller_nid": "ingestion_pipeline_ingestionpipeline_ingest_from_url", "callee": "split", "is_member_call": true, "source_file": "C:\\Users\\unicentrale\\Downloads\\antigravity\\services\\gravity-api\\app\\ingestion\\pipeline.py", "source_location": "L255"}, {"caller_nid": "ingestion_pipeline_ingestionpipeline_ingest_bytes", "callee": "uuid4", "is_member_call": true, "source_file": "C:\\Users\\unicentrale\\Downloads\\antigravity\\services\\gravity-api\\app\\ingestion\\pipeline.py", "source_location": "L295"}, {"caller_nid": "ingestion_pipeline_ingestionpipeline_ingest_bytes", "callee": "info", "is_member_call": true, "source_file": "C:\\Users\\unicentrale\\Downloads\\antigravity\\services\\gravity-api\\app\\ingestion\\pipeline.py", "source_location": "L297"}, {"caller_nid": "ingestion_pipeline_ingestionpipeline_ingest_bytes", "callee": "process", "is_member_call": true, "source_file": "C:\\Users\\unicentrale\\Downloads\\antigravity\\services\\gravity-api\\app\\ingestion\\pipeline.py", "source_location": "L306"}, {"caller_nid": "ingestion_pipeline_ingestionpipeline_ingest_bytes", "callee": "strip", "is_member_call": true, "source_file": "C:\\Users\\unicentrale\\Downloads\\antigravity\\services\\gravity-api\\app\\ingestion\\pipeline.py", "source_location": "L308"}, {"caller_nid": "ingestion_pipeline_ingestionpipeline_ingest_bytes", "callee": "warning", "is_member_call": true, "source_file": "C:\\Users\\unicentrale\\Downloads\\antigravity\\services\\gravity-api\\app\\ingestion\\pipeline.py", "source_location": "L309"}, {"caller_nid": "ingestion_pipeline_ingestionpipeline_ingest_bytes", "callee": "extract", "is_member_call": true, "source_file": "C:\\Users\\unicentrale\\Downloads\\antigravity\\services\\gravity-api\\app\\ingestion\\pipeline.py", "source_location": "L317"}, {"caller_nid": "ingestion_pipeline_ingestionpipeline_ingest_bytes", "callee": "parse_sec_form", "is_member_call": false, "source_file": "C:\\Users\\unicentrale\\Downloads\\antigravity\\services\\gravity-api\\app\\ingestion\\pipeline.py", "source_location": "L337"}, {"caller_nid": "ingestion_pipeline_ingestionpipeline_ingest_bytes", "callee": "info", "is_member_call": true, "source_file": "C:\\Users\\unicentrale\\Downloads\\antigravity\\services\\gravity-api\\app\\ingestion\\pipeline.py", "source_location": "L342"}, {"caller_nid": "ingestion_pipeline_ingestionpipeline_ingest_bytes", "callee": "get", "is_member_call": true, "source_file": "C:\\Users\\unicentrale\\Downloads\\antigravity\\services\\gravity-api\\app\\ingestion\\pipeline.py", "source_location": "L345"}, {"caller_nid": "ingestion_pipeline_ingestionpipeline_ingest_bytes", "callee": "keys", "is_member_call": true, "source_file": "C:\\Users\\unicentrale\\Downloads\\antigravity\\services\\gravity-api\\app\\ingestion\\pipeline.py", "source_location": "L346"}, {"caller_nid": "ingestion_pipeline_ingestionpipeline_ingest_bytes", "callee": "warning", "is_member_call": true, "source_file": "C:\\Users\\unicentrale\\Downloads\\antigravity\\services\\gravity-api\\app\\ingestion\\pipeline.py", "source_location": "L349"}, {"caller_nid": "ingestion_pipeline_ingestionpipeline_ingest_bytes", "callee": "run_in_executor", "is_member_call": true, "source_file": "C:\\Users\\unicentrale\\Downloads\\antigravity\\services\\gravity-api\\app\\ingestion\\pipeline.py", "source_location": "L352"}, {"caller_nid": "ingestion_pipeline_ingestionpipeline_ingest_bytes", "callee": "get_event_loop", "is_member_call": true, "source_file": "C:\\Users\\unicentrale\\Downloads\\antigravity\\services\\gravity-api\\app\\ingestion\\pipeline.py", "source_location": "L352"}, {"caller_nid": "ingestion_pipeline_ingestionpipeline_ingest_bytes", "callee": "extract", "is_member_call": true, "source_file": "C:\\Users\\unicentrale\\Downloads\\antigravity\\services\\gravity-api\\app\\ingestion\\pipeline.py", "source_location": "L360"}, {"caller_nid": "ingestion_pipeline_ingestionpipeline_ingest_bytes", "callee": "chunk_document", "is_member_call": true, "source_file": "C:\\Users\\unicentrale\\Downloads\\antigravity\\services\\gravity-api\\app\\ingestion\\pipeline.py", "source_location": "L363"}, {"caller_nid": "ingestion_pipeline_ingestionpipeline_ingest_bytes", "callee": "info", "is_member_call": true, "source_file": "C:\\Users\\unicentrale\\Downloads\\antigravity\\services\\gravity-api\\app\\ingestion\\pipeline.py", "source_location": "L370"}, {"caller_nid": "ingestion_pipeline_ingestionpipeline_ingest_bytes", "callee": "enrich", "is_member_call": true, "source_file": "C:\\Users\\unicentrale\\Downloads\\antigravity\\services\\gravity-api\\app\\ingestion\\pipeline.py", "source_location": "L383"}, {"caller_nid": "ingestion_pipeline_ingestionpipeline_ingest_bytes", "callee": "warning", "is_member_call": true, "source_file": "C:\\Users\\unicentrale\\Downloads\\antigravity\\services\\gravity-api\\app\\ingestion\\pipeline.py", "source_location": "L387"}, {"caller_nid": "ingestion_pipeline_ingestionpipeline_ingest_bytes", "callee": "build_summaries", "is_member_call": true, "source_file": "C:\\Users\\unicentrale\\Downloads\\antigravity\\services\\gravity-api\\app\\ingestion\\pipeline.py", "source_location": "L393"}, {"caller_nid": "ingestion_pipeline_ingestionpipeline_ingest_bytes", "callee": "info", "is_member_call": true, "source_file": "C:\\Users\\unicentrale\\Downloads\\antigravity\\services\\gravity-api\\app\\ingestion\\pipeline.py", "source_location": "L396"}, {"caller_nid": "ingestion_pipeline_ingestionpipeline_ingest_bytes", "callee": "warning", "is_member_call": true, "source_file": "C:\\Users\\unicentrale\\Downloads\\antigravity\\services\\gravity-api\\app\\ingestion\\pipeline.py", "source_location": "L402"}, {"caller_nid": "ingestion_pipeline_ingestionpipeline_ingest_bytes", "callee": "get", "is_member_call": true, "source_file": "C:\\Users\\unicentrale\\Downloads\\antigravity\\services\\gravity-api\\app\\ingestion\\pipeline.py", "source_location": "L436"}, {"caller_nid": "ingestion_pipeline_ingestionpipeline_ingest_bytes", "callee": "get", "is_member_call": true, "source_file": "C:\\Users\\unicentrale\\Downloads\\antigravity\\services\\gravity-api\\app\\ingestion\\pipeline.py", "source_location": "L437"}, {"caller_nid": "ingestion_pipeline_ingestionpipeline_ingest_bytes", "callee": "get", "is_member_call": true, "source_file": "C:\\Users\\unicentrale\\Downloads\\antigravity\\services\\gravity-api\\app\\ingestion\\pipeline.py", "source_location": "L438"}, {"caller_nid": "ingestion_pipeline_ingestionpipeline_ingest_bytes", "callee": "get", "is_member_call": true, "source_file": "C:\\Users\\unicentrale\\Downloads\\antigravity\\services\\gravity-api\\app\\ingestion\\pipeline.py", "source_location": "L439"}, {"caller_nid": "ingestion_pipeline_ingestionpipeline_ingest_bytes", "callee": "info", "is_member_call": true, "source_file": "C:\\Users\\unicentrale\\Downloads\\antigravity\\services\\gravity-api\\app\\ingestion\\pipeline.py", "source_location": "L445"}, {"caller_nid": "ingestion_pipeline_ingestionpipeline_ingest_bytes", "callee": "items", "is_member_call": true, "source_file": "C:\\Users\\unicentrale\\Downloads\\antigravity\\services\\gravity-api\\app\\ingestion\\pipeline.py", "source_location": "L445"}, {"caller_nid": "ingestion_pipeline_ingestionpipeline_parallel_index", "callee": "gather", "is_member_call": true, "source_file": "C:\\Users\\unicentrale\\Downloads\\antigravity\\services\\gravity-api\\app\\ingestion\\pipeline.py", "source_location": "L615"}, {"caller_nid": "ingestion_pipeline_ingestionpipeline_parallel_index", "callee": "run_vector", "is_member_call": false, "source_file": "C:\\Users\\unicentrale\\Downloads\\antigravity\\services\\gravity-api\\app\\ingestion\\pipeline.py", "source_location": "L616"}, {"caller_nid": "ingestion_pipeline_ingestionpipeline_parallel_index", "callee": "run_keyword", "is_member_call": false, "source_file": "C:\\Users\\unicentrale\\Downloads\\antigravity\\services\\gravity-api\\app\\ingestion\\pipeline.py", "source_location": "L617"}, {"caller_nid": "ingestion_pipeline_ingestionpipeline_parallel_index", "callee": "run_graph", "is_member_call": false, "source_file": "C:\\Users\\unicentrale\\Downloads\\antigravity\\services\\gravity-api\\app\\ingestion\\pipeline.py", "source_location": "L618"}, {"caller_nid": "ingestion_pipeline_ingestionpipeline_parallel_index", "callee": "run_structured", "is_member_call": false, "source_file": "C:\\Users\\unicentrale\\Downloads\\antigravity\\services\\gravity-api\\app\\ingestion\\pipeline.py", "source_location": "L619"}, {"caller_nid": "ingestion_pipeline_ingestionpipeline_parallel_index", "callee": "run_page_index", "is_member_call": false, "source_file": "C:\\Users\\unicentrale\\Downloads\\antigravity\\services\\gravity-api\\app\\ingestion\\pipeline.py", "source_location": "L620"}, {"caller_nid": "ingestion_pipeline_ingestionpipeline_parallel_index", "callee": "run_tables", "is_member_call": false, "source_file": "C:\\Users\\unicentrale\\Downloads\\antigravity\\services\\gravity-api\\app\\ingestion\\pipeline.py", "source_location": "L621"}, {"caller_nid": "ingestion_pipeline_ingestionpipeline_parallel_index", "callee": "run_xbrl", "is_member_call": false, "source_file": "C:\\Users\\unicentrale\\Downloads\\antigravity\\services\\gravity-api\\app\\ingestion\\pipeline.py", "source_location": "L622"}, {"caller_nid": "ingestion_pipeline_ingestionpipeline_save_document_record", "callee": "db_session_factory", "is_member_call": true, "source_file": "C:\\Users\\unicentrale\\Downloads\\antigravity\\services\\gravity-api\\app\\ingestion\\pipeline.py", "source_location": "L654"}, {"caller_nid": "ingestion_pipeline_ingestionpipeline_save_document_record", "callee": "get", "is_member_call": true, "source_file": "C:\\Users\\unicentrale\\Downloads\\antigravity\\services\\gravity-api\\app\\ingestion\\pipeline.py", "source_location": "L656"}, {"caller_nid": "ingestion_pipeline_ingestionpipeline_save_document_record", "callee": "delete", "is_member_call": true, "source_file": "C:\\Users\\unicentrale\\Downloads\\antigravity\\services\\gravity-api\\app\\ingestion\\pipeline.py", "source_location": "L658"}, {"caller_nid": "ingestion_pipeline_ingestionpipeline_save_document_record", "callee": "flush", "is_member_call": true, "source_file": "C:\\Users\\unicentrale\\Downloads\\antigravity\\services\\gravity-api\\app\\ingestion\\pipeline.py", "source_location": "L659"}, {"caller_nid": "ingestion_pipeline_ingestionpipeline_save_document_record", "callee": "add", "is_member_call": true, "source_file": "C:\\Users\\unicentrale\\Downloads\\antigravity\\services\\gravity-api\\app\\ingestion\\pipeline.py", "source_location": "L661"}, {"caller_nid": "ingestion_pipeline_ingestionpipeline_save_document_record", "callee": "Document", "is_member_call": false, "source_file": "C:\\Users\\unicentrale\\Downloads\\antigravity\\services\\gravity-api\\app\\ingestion\\pipeline.py", "source_location": "L661"}, {"caller_nid": "ingestion_pipeline_ingestionpipeline_save_document_record", "callee": "utcnow", "is_member_call": true, "source_file": "C:\\Users\\unicentrale\\Downloads\\antigravity\\services\\gravity-api\\app\\ingestion\\pipeline.py", "source_location": "L674"}, {"caller_nid": "ingestion_pipeline_ingestionpipeline_save_document_record", "callee": "add", "is_member_call": true, "source_file": "C:\\Users\\unicentrale\\Downloads\\antigravity\\services\\gravity-api\\app\\ingestion\\pipeline.py", "source_location": "L681"}, {"caller_nid": "ingestion_pipeline_ingestionpipeline_save_document_record", "callee": "Chunk", "is_member_call": false, "source_file": "C:\\Users\\unicentrale\\Downloads\\antigravity\\services\\gravity-api\\app\\ingestion\\pipeline.py", "source_location": "L681"}, {"caller_nid": "ingestion_pipeline_ingestionpipeline_save_document_record", "callee": "commit", "is_member_call": true, "source_file": "C:\\Users\\unicentrale\\Downloads\\antigravity\\services\\gravity-api\\app\\ingestion\\pipeline.py", "source_location": "L694"}, {"caller_nid": "ingestion_pipeline_ingestionpipeline_save_document_record", "callee": "warning", "is_member_call": true, "source_file": "C:\\Users\\unicentrale\\Downloads\\antigravity\\services\\gravity-api\\app\\ingestion\\pipeline.py", "source_location": "L697"}]}